[
  {
    "id": -844909032,
    "legajo": null,
    "apellido": "MACIEL",
    "nombre": "Daiana Nicole",
    "cuil": "27-44649656-0",
    "categoria": "Personal fijo",
    "tarea": "Camarera",
    "fecha_ingreso": null,
    "cbu": null,
    "activo": true,
    "tipo_personal": "fijo"
  },
  {
    "id": -5745466,
    "legajo": null,
    "apellido": "KIENER",
    "nombre": "Marcos Javier",
    "cuil": "20-33022640-5",
    "categoria": "Personal fijo",
    "tarea": "Camarero",
    "fecha_ingreso": null,
    "cbu": null,
    "activo": true,
    "tipo_personal": "fijo"
  },
  {
    "id": -599178841,
    "legajo": null,
    "apellido": "VACCARO",
    "nombre": "Veronica Del Carmen",
    "cuil": "27-32092301-3",
    "categoria": "Personal fijo",
    "tarea": "Cocinera",
    "fecha_ingreso": null,
    "cbu": null,
    "activo": true,
    "tipo_personal": "fijo"
  },
  {
    "id": -304938111,
    "legajo": null,
    "apellido": "MUZZIO",
    "nombre": "Elizabeth Gisela",
    "cuil": "27-29095855-0",
    "categoria": "Personal fijo",
    "tarea": "Cocinera",
    "fecha_ingreso": null,
    "cbu": null,
    "activo": true,
    "tipo_personal": "fijo"
  },
  {
    "id": -980578259,
    "legajo": null,
    "apellido": "ALMIRON",
    "nombre": "Carlos Dario",
    "cuil": "20-30525510-7",
    "categoria": "Personal fijo",
    "tarea": "Cocinero",
    "fecha_ingreso": null,
    "cbu": null,
    "activo": true,
    "tipo_personal": "fijo"
  },
  {
    "id": -786766303,
    "legajo": null,
    "apellido": "ISASMENDI",
    "nombre": "Salvador Maria",
    "cuil": "20-29237797-6",
    "categoria": "Personal fijo",
    "tarea": "Cocinero",
    "fecha_ingreso": null,
    "cbu": null,
    "activo": true,
    "tipo_personal": "fijo"
  },
  {
    "id": -791204341,
    "legajo": null,
    "apellido": "ORTIZ",
    "nombre": "Cesar Hernan",
    "cuil": "20-24288079-0",
    "categoria": "Personal fijo",
    "tarea": "Bachero",
    "fecha_ingreso": null,
    "cbu": null,
    "activo": true,
    "tipo_personal": "fijo"
  },
  {
    "id": -890791387,
    "legajo": null,
    "apellido": "ZACARIAS",
    "nombre": "Walter Gaston",
    "cuil": "20-34235147-7",
    "categoria": "Personal fijo",
    "tarea": "Bachero",
    "fecha_ingreso": null,
    "cbu": null,
    "activo": true,
    "tipo_personal": "fijo"
  },
  {
    "id": -679243229,
    "legajo": null,
    "apellido": "PAZ",
    "nombre": "Fernando Ezequiel",
    "cuil": "20-36387016-4",
    "categoria": "Personal fijo",
    "tarea": "Bachero",
    "fecha_ingreso": null,
    "cbu": null,
    "activo": true,
    "tipo_personal": "fijo"
  },
  {
    "id": -159798236,
    "legajo": null,
    "apellido": "DOMINGUEZ",
    "nombre": "Alejandro Sebastian",
    "cuil": "20-34155897-3",
    "categoria": "Personal fijo",
    "tarea": "Bachero",
    "fecha_ingreso": null,
    "cbu": null,
    "activo": true,
    "tipo_personal": "fijo"
  },
  {
    "id": -931693133,
    "legajo": null,
    "apellido": "SCIOLLA",
    "nombre": "Santiago Ariel",
    "cuil": "23-44391829-9",
    "categoria": "Personal fijo",
    "tarea": "Camarero",
    "fecha_ingreso": null,
    "cbu": null,
    "activo": true,
    "tipo_personal": "fijo"
  },
  {
    "id": -3680565,
    "legajo": null,
    "apellido": "SCISCENTE VERA",
    "nombre": "Ivan Alejo",
    "cuil": "20-45523894-4",
    "categoria": "Personal fijo",
    "tarea": "Camarero",
    "fecha_ingreso": null,
    "cbu": null,
    "activo": true,
    "tipo_personal": "fijo"
  },
  {
    "id": -599668702,
    "legajo": null,
    "apellido": "MERCAU",
    "nombre": "Gisela Carolina",
    "cuil": "23-25240830-4",
    "categoria": "Personal fijo",
    "tarea": "Capitan de salon",
    "fecha_ingreso": null,
    "cbu": null,
    "activo": true,
    "tipo_personal": "fijo"
  },
  {
    "id": -238864188,
    "legajo": null,
    "apellido": "RATTO",
    "nombre": "Gustavo German",
    "cuil": "20-29885343-5",
    "categoria": "Personal fijo",
    "tarea": "Jefe de Cocina",
    "fecha_ingreso": null,
    "cbu": null,
    "activo": true,
    "tipo_personal": "fijo"
  },
  {
    "id": -712628743,
    "legajo": null,
    "apellido": "MORENO",
    "nombre": "Sergio Gustavo",
    "cuil": "20-92704028-0",
    "categoria": "Personal fijo",
    "tarea": "Jefe de Cocina",
    "fecha_ingreso": null,
    "cbu": null,
    "activo": true,
    "tipo_personal": "fijo"
  },
  {
    "id": -866522826,
    "legajo": null,
    "apellido": "CACERES",
    "nombre": "Fernando Miqueas",
    "cuil": "20-39136618-8",
    "categoria": "Personal fijo",
    "tarea": "Jefe de Cocina",
    "fecha_ingreso": null,
    "cbu": null,
    "activo": true,
    "tipo_personal": "fijo"
  },
  {
    "id": -40616657,
    "legajo": null,
    "apellido": "VILLALBA",
    "nombre": "Gabriela Soledad",
    "cuil": "27-37352193-6",
    "categoria": "Personal fijo",
    "tarea": "Jefe de Servicio",
    "fecha_ingreso": null,
    "cbu": null,
    "activo": true,
    "tipo_personal": "fijo"
  },
  {
    "id": -862115702,
    "legajo": null,
    "apellido": "MALICA FUENZALIDA",
    "nombre": "Damian Alfredo",
    "cuil": "20-40843942-7",
    "categoria": "Personal fijo",
    "tarea": "Jefe de Servicio",
    "fecha_ingreso": null,
    "cbu": null,
    "activo": true,
    "tipo_personal": "fijo"
  },
  {
    "id": -84781657,
    "legajo": null,
    "apellido": "VEGA TORTONE",
    "nombre": "Walter Maximiliano",
    "cuil": "20-18903779-2",
    "categoria": "Personal fijo",
    "tarea": "Maitre",
    "fecha_ingreso": null,
    "cbu": null,
    "activo": true,
    "tipo_personal": "fijo"
  },
  {
    "id": -248474225,
    "legajo": null,
    "apellido": "CARONNI",
    "nombre": "Diego Ariel",
    "cuil": "20-23704000-8",
    "categoria": "Personal fijo",
    "tarea": "Maitre",
    "fecha_ingreso": null,
    "cbu": null,
    "activo": true,
    "tipo_personal": "fijo"
  },
  {
    "id": -820715607,
    "legajo": null,
    "apellido": "VILLAREAL",
    "nombre": "Romina Vanesa",
    "cuil": "27-33687238-9",
    "categoria": "Personal fijo",
    "tarea": "Maitre",
    "fecha_ingreso": null,
    "cbu": null,
    "activo": true,
    "tipo_personal": "fijo"
  },
  {
    "id": -907851035,
    "legajo": null,
    "apellido": "BORNASCHELLA",
    "nombre": "Pedro Antonio",
    "cuil": "20-20015518-2",
    "categoria": "Personal fijo",
    "tarea": "Bachero",
    "fecha_ingreso": null,
    "cbu": null,
    "activo": true,
    "tipo_personal": "fijo"
  },
  {
    "id": -650822007,
    "legajo": null,
    "apellido": "VIDELA",
    "nombre": "Ayelen Valeria Z.",
    "cuil": "27-46821915-3",
    "categoria": "Personal fijo",
    "tarea": "Camarero",
    "fecha_ingreso": null,
    "cbu": null,
    "activo": true,
    "tipo_personal": "fijo"
  },
  {
    "id": -460259453,
    "legajo": null,
    "apellido": "PEDRO",
    "nombre": "Matias Alejandro",
    "cuil": "20-38799425-5",
    "categoria": "Personal fijo",
    "tarea": "Cocinero",
    "fecha_ingreso": null,
    "cbu": null,
    "activo": true,
    "tipo_personal": "fijo"
  }
]